datus_sqlalchemy/__init__.py
datus_sqlalchemy/connector.py
datus_sqlalchemy-0.1.2.dist-info/METADATA
datus_sqlalchemy-0.1.2.dist-info/WHEEL
datus_sqlalchemy-0.1.2.dist-info/RECORD
