Metadata-Version: 2.4
Name: datus-sqlalchemy
Version: 0.1.2
Summary: SQLAlchemy base connector for Datus database adapters
Project-URL: Homepage, https://github.com/Datus-ai/datus-db-adapters
Project-URL: Repository, https://github.com/Datus-ai/datus-db-adapters
Project-URL: Issues, https://github.com/Datus-ai/datus-db-adapters/issues
Author-email: DatusAI <support@datus.ai>
License: Apache-2.0
Keywords: adapter,database,datus,sqlalchemy
Classifier: Development Status :: 4 - Beta
Classifier: Intended Audience :: Developers
Classifier: License :: OSI Approved :: Apache Software License
Classifier: Programming Language :: Python :: 3
Classifier: Programming Language :: Python :: 3.12
Requires-Python: >=3.12
Requires-Dist: datus-agent>0.2.1
Requires-Dist: pandas>=2.1.4
Requires-Dist: pyarrow<19.0.0,>=14.0.0
Requires-Dist: sqlalchemy>=2.0.23
